landlensdb/__init__.py
landlensdb/geoclasses/__init__.py
landlensdb/geoclasses/geoimageframe.py
landlensdb/handlers/__init__.py
landlensdb/handlers/cloud.py
landlensdb/handlers/db.py
landlensdb/handlers/image.py
landlensdb/process/__init__.py
landlensdb/process/road_network.py
landlensdb/process/snap.py
landlensdb-0.1.4.dist-info/licenses/LICENSE.md
landlensdb-0.1.4.dist-info/METADATA
landlensdb-0.1.4.dist-info/WHEEL
landlensdb-0.1.4.dist-info/top_level.txt
landlensdb-0.1.4.dist-info/RECORD
