Metadata-Version: 2.4
Name: landlensdb
Version: 0.1.4
Summary: Geospatial image handling and management
Author-email: Joseph Emile Honour Percival <ipercival@gmail.com>
Maintainer: Narumasa Tsutsumida
Maintainer-email: Joseph Emile Honour Percival <ipercival@gmail.com>
License: MIT
Project-URL: Bug Tracker, https://github.com/landlensdb/landlensdb
Project-URL: Source, https://github.com/landlensdb/landlensdb
Keywords: gis,geospatial,images
Classifier: Programming Language :: Python :: 3
Classifier: License :: OSI Approved :: MIT License
Classifier: Operating System :: OS Independent
Requires-Python: >=3.10
License-File: LICENSE.md
Requires-Dist: geoalchemy2>=0.17.1
Requires-Dist: geopandas>=1.0.1
Requires-Dist: mapbox_vector_tile>=2.1.0
Requires-Dist: numpy>=2.2.4
Requires-Dist: osmnx>=2.0.1
Requires-Dist: pandas>=2.2.0
Requires-Dist: psycopg2>=2.9.9
Requires-Dist: pyogrio>=0.10.0
Requires-Dist: shapely>=2.0.0
Requires-Dist: requests>=2.32.0
Requires-Dist: SQLAlchemy>=2.0.25
Requires-Dist: folium>=0.19.1
Requires-Dist: Rtree>=1.4.0
Requires-Dist: pytz>=2025.1
Requires-Dist: timezonefinder>=6.5.8
Requires-Dist: Pillow>=11.0.0
Requires-Dist: tqdm>=4.67.1
Provides-Extra: dev
Requires-Dist: pytest>=8.3.5; extra == "dev"
Requires-Dist: pytest-cov==6.0.0; extra == "dev"
Requires-Dist: jupyter~=1.0.0; extra == "dev"
Requires-Dist: pre-commit~=3.6.0; extra == "dev"
Requires-Dist: python-dotenv==1.0.1; extra == "dev"
Provides-Extra: docs
Requires-Dist: mkdocs>=1.4.0; extra == "docs"
Requires-Dist: mkdocs-material>=9.0.0; extra == "docs"
Requires-Dist: mkdocs-jupyter>=0.24.0; extra == "docs"
Requires-Dist: mkdocstrings>=0.21.0; extra == "docs"
Requires-Dist: mkdocstrings-python>=0.10.0; extra == "docs"
Requires-Dist: mkdocs-git-revision-date-plugin>=0.3.2; extra == "docs"
Requires-Dist: pymdown-extensions>=9.10; extra == "docs"
Dynamic: license-file
